lab/__init__.py
lab/cupy_backend.py
lab/numpy_backend.py
lab/py.typed
lab/torch_backend.py
linalg_backends-0.0.1b0.dist-info/LICENSE
linalg_backends-0.0.1b0.dist-info/METADATA
linalg_backends-0.0.1b0.dist-info/WHEEL
linalg_backends-0.0.1b0.dist-info/top_level.txt
linalg_backends-0.0.1b0.dist-info/RECORD
