Metadata-Version: 2.1
Name: linalg-backends
Version: 0.0.1b0
Summary: Linear Algebra Backends: a lightweight interface for linear algebra engines.
Author-email: Aaron Mishkin <amishkin@cs.stanford.edu>
License: MIT License        
Project-URL: Homepage, https://github.com/aaronpmishkin/lab
Project-URL: Bug Tracker, https://github.com/aaronpmishkin/lab/issues
Classifier: Programming Language :: Python :: 3
Classifier: License :: OSI Approved :: MIT License
Classifier: Operating System :: OS Independent
Requires-Python: >=3.7
License-File: LICENSE
Requires-Dist: numpy
Requires-Dist: torch
Requires-Dist: opt-einsum
